latexdl/__init__.py
latexdl/__main__.py
latexdl/_bibtex.py
latexdl/_cache.py
latexdl/_fix_urls.py
latexdl/_metadata.py
latexdl/_types.py
latexdl/expand.py
latexdl/main.py
latexdl/mcp.py
latexdl/strip.py
latexdl-2.2.0.dist-info/METADATA
latexdl-2.2.0.dist-info/WHEEL
latexdl-2.2.0.dist-info/entry_points.txt
latexdl-2.2.0.dist-info/RECORD
